{"id":62895254,"node_id":"MDEwOlJlcG9zaXRvcnk2Mjg5NTI1NA==","name":"Thesis-ITS","full_name":"robertoguazon/Thesis-ITS","private":false,"owner":{"login":"robertoguazon","id":11959839,"node_id":"MDQ6VXNlcjExOTU5ODM5","gravatar_id":"","url":"https://api.github.com/users/robertoguazon","type":"User","site_admin":false},"description":"Intelligent Tutoring System","fork":false,"url":"https://api.github.com/repos/robertoguazon/Thesis-ITS","created_at":"2016-07-08T14:37:58Z","updated_at":"2020-05-30T16:54:02Z","pushed_at":"2016-12-07T11:20:05Z","size":267436,"stargazers_count":5,"watchers_count":5,"language":"Java","has_issues":true,"has_projects":true,"has_downloads":true,"has_wiki":true,"has_pages":false,"forks_count":4,"archived":false,"disabled":false,"open_issues_count":0,"forks":4,"open_issues":0,"watchers":5,"default_branch":"master","permissions":{"admin":false,"push":false,"pull":true},"temp_clone_token":"","network_count":4,"subscribers_count":3}