{"id":39652472,"node_id":"MDEwOlJlcG9zaXRvcnkzOTY1MjQ3Mg==","name":"ebean-querybean","full_name":"ebean-orm/ebean-querybean","private":false,"owner":{"login":"ebean-orm","id":3973790,"node_id":"MDEyOk9yZ2FuaXphdGlvbjM5NzM3OTA=","gravatar_id":"","url":"https://api.github.com/users/ebean-orm","type":"Organization","site_admin":false},"description":"Required dependency for generated \"Query Beans\".  Query beans provide type safe query construction.","fork":false,"url":"https://api.github.com/repos/ebean-orm/ebean-querybean","created_at":"2015-07-24T19:17:54Z","updated_at":"2020-06-19T11:32:16Z","pushed_at":"2020-06-19T11:32:14Z","homepage":"https://ebean.io/docs/query/query-beans","size":306,"stargazers_count":9,"watchers_count":9,"language":"Java","has_issues":true,"has_projects":true,"has_downloads":true,"has_wiki":true,"has_pages":false,"forks_count":3,"archived":false,"disabled":false,"open_issues_count":2,"license":{"key":"apache-2.0","name":"Apache License 2.0","spdx_id":"Apache-2.0","url":"https://api.github.com/licenses/apache-2.0","node_id":"MDc6TGljZW5zZTI="},"forks":3,"open_issues":2,"watchers":9,"default_branch":"master","permissions":{"admin":false,"push":false,"pull":true},"temp_clone_token":"","organization":{"login":"ebean-orm","id":3973790,"node_id":"MDEyOk9yZ2FuaXphdGlvbjM5NzM3OTA=","gravatar_id":"","url":"https://api.github.com/users/ebean-orm","type":"Organization","site_admin":false},"network_count":3,"subscribers_count":7}