{"id":42409975,"node_id":"MDEwOlJlcG9zaXRvcnk0MjQwOTk3NQ==","name":"BLT","full_name":"netfishers-onl/BLT","private":false,"owner":{"login":"netfishers-onl","id":14115682,"node_id":"MDEyOk9yZ2FuaXphdGlvbjE0MTE1Njgy","gravatar_id":"","url":"https://api.github.com/users/netfishers-onl","type":"Organization","site_admin":false},"description":"BLT The BGP Linkstate Topographer","fork":false,"url":"https://api.github.com/repos/netfishers-onl/BLT","created_at":"2015-09-13T19:37:24Z","updated_at":"2020-02-14T16:02:15Z","pushed_at":"2016-05-19T09:06:30Z","size":27298,"stargazers_count":13,"watchers_count":13,"language":"Java","has_issues":true,"has_projects":true,"has_downloads":true,"has_wiki":true,"has_pages":false,"forks_count":7,"archived":false,"disabled":false,"open_issues_count":3,"forks":7,"open_issues":3,"watchers":13,"default_branch":"master","permissions":{"admin":false,"push":false,"pull":true},"temp_clone_token":"","organization":{"login":"netfishers-onl","id":14115682,"node_id":"MDEyOk9yZ2FuaXphdGlvbjE0MTE1Njgy","gravatar_id":"","url":"https://api.github.com/users/netfishers-onl","type":"Organization","site_admin":false},"network_count":7,"subscribers_count":7}