{"id":12075667,"node_id":"MDEwOlJlcG9zaXRvcnkxMjA3NTY2Nw==","name":"multipart-handler","full_name":"DanielN/multipart-handler","private":false,"owner":{"login":"DanielN","id":102627,"node_id":"MDQ6VXNlcjEwMjYyNw==","gravatar_id":"","url":"https://api.github.com/users/DanielN","type":"User","site_admin":false},"description":"MIME multipart encoder/decoder for Java","fork":false,"url":"https://api.github.com/repos/DanielN/multipart-handler","created_at":"2013-08-13T07:13:05Z","updated_at":"2019-10-20T13:14:31Z","pushed_at":"2013-08-21T08:34:22Z","size":128,"stargazers_count":6,"watchers_count":6,"language":"Java","has_issues":true,"has_projects":true,"has_downloads":true,"has_wiki":true,"has_pages":false,"forks_count":4,"archived":false,"disabled":false,"open_issues_count":2,"forks":4,"open_issues":2,"watchers":6,"default_branch":"master","permissions":{"admin":false,"push":false,"pull":true},"temp_clone_token":"","network_count":4,"subscribers_count":1}