{"id":62813532,"node_id":"MDEwOlJlcG9zaXRvcnk2MjgxMzUzMg==","name":"Quiz","full_name":"zhzy0077/Quiz","private":false,"owner":{"login":"zhzy0077","id":8717471,"node_id":"MDQ6VXNlcjg3MTc0NzE=","gravatar_id":"","url":"https://api.github.com/users/zhzy0077","type":"User","site_admin":false},"description":"考试系统","fork":false,"url":"https://api.github.com/repos/zhzy0077/Quiz","created_at":"2016-07-07T14:32:35Z","updated_at":"2020-06-19T07:33:28Z","pushed_at":"2019-08-05T07:52:00Z","homepage":"","size":1745,"stargazers_count":6,"watchers_count":6,"language":"Java","has_issues":true,"has_projects":true,"has_downloads":true,"has_wiki":true,"has_pages":false,"forks_count":1,"archived":true,"disabled":false,"open_issues_count":0,"forks":1,"open_issues":0,"watchers":6,"default_branch":"master","permissions":{"admin":false,"push":false,"pull":true},"temp_clone_token":"","network_count":1,"subscribers_count":2}