{"id":63366191,"node_id":"MDEwOlJlcG9zaXRvcnk2MzM2NjE5MQ==","name":"aws-v4-signer-java","full_name":"lucasweb78/aws-v4-signer-java","private":false,"owner":{"login":"lucasweb78","id":868181,"node_id":"MDQ6VXNlcjg2ODE4MQ==","gravatar_id":"","url":"https://api.github.com/users/lucasweb78","type":"User","site_admin":false},"description":"aws-v4-signer-java is a lightweight, zero-dependency implementation of the AWS V4 signing algorithm required by many of the AWS services.","fork":false,"url":"https://api.github.com/repos/lucasweb78/aws-v4-signer-java","created_at":"2016-07-14T20:07:15Z","updated_at":"2020-06-04T15:32:12Z","pushed_at":"2019-08-07T08:28:02Z","size":82,"stargazers_count":30,"watchers_count":30,"language":"Java","has_issues":true,"has_projects":true,"has_downloads":true,"has_wiki":true,"has_pages":false,"forks_count":19,"archived":false,"disabled":false,"open_issues_count":8,"license":{"key":"apache-2.0","name":"Apache License 2.0","spdx_id":"Apache-2.0","url":"https://api.github.com/licenses/apache-2.0","node_id":"MDc6TGljZW5zZTI="},"forks":19,"open_issues":8,"watchers":30,"default_branch":"master","permissions":{"admin":false,"push":false,"pull":true},"temp_clone_token":"","network_count":19,"subscribers_count":9}