{"id":174248734,"node_id":"MDEwOlJlcG9zaXRvcnkxNzQyNDg3MzQ=","name":"java-crypto-utils","full_name":"tunjos/java-crypto-utils","private":false,"owner":{"login":"tunjos","id":971768,"node_id":"MDQ6VXNlcjk3MTc2OA==","gravatar_id":"","url":"https://api.github.com/users/tunjos","type":"User","site_admin":false},"description":"Java Cryptographic, Encoding and Hash Utilities","fork":false,"url":"https://api.github.com/repos/tunjos/java-crypto-utils","created_at":"2019-03-07T01:30:28Z","updated_at":"2020-01-14T08:39:06Z","pushed_at":"2019-03-17T23:38:58Z","homepage":"https://learn.tunjos.co/cryptography","size":31,"stargazers_count":15,"watchers_count":15,"language":"Java","has_issues":true,"has_projects":true,"has_downloads":true,"has_wiki":true,"has_pages":false,"forks_count":4,"archived":false,"disabled":false,"open_issues_count":0,"forks":4,"open_issues":0,"watchers":15,"default_branch":"master","permissions":{"admin":false,"push":false,"pull":true},"temp_clone_token":"","network_count":4,"subscribers_count":1}