{"id":130929792,"node_id":"MDEwOlJlcG9zaXRvcnkxMzA5Mjk3OTI=","name":"springbootRedis","full_name":"JayTange/springbootRedis","private":false,"owner":{"login":"JayTange","id":25770504,"node_id":"MDQ6VXNlcjI1NzcwNTA0","gravatar_id":"","url":"https://api.github.com/users/JayTange","type":"User","site_admin":false},"description":"springboot与redis的集合","fork":false,"url":"https://api.github.com/repos/JayTange/springbootRedis","created_at":"2018-04-25T00:43:06Z","updated_at":"2020-06-22T07:14:15Z","pushed_at":"2018-05-06T10:34:45Z","size":19,"stargazers_count":132,"watchers_count":132,"language":"Java","has_issues":true,"has_projects":true,"has_downloads":true,"has_wiki":true,"has_pages":false,"forks_count":74,"archived":false,"disabled":false,"open_issues_count":1,"license":{"key":"apache-2.0","name":"Apache License 2.0","spdx_id":"Apache-2.0","url":"https://api.github.com/licenses/apache-2.0","node_id":"MDc6TGljZW5zZTI="},"forks":74,"open_issues":1,"watchers":132,"default_branch":"master","permissions":{"admin":false,"push":false,"pull":true},"temp_clone_token":"","network_count":74,"subscribers_count":2}