{"id":136254218,"node_id":"MDEwOlJlcG9zaXRvcnkxMzYyNTQyMTg=","name":"sample-zuul-swagger2","full_name":"SpringCloud/sample-zuul-swagger2","private":false,"owner":{"login":"SpringCloud","id":15123112,"node_id":"MDEyOk9yZ2FuaXphdGlvbjE1MTIzMTEy","gravatar_id":"","url":"https://api.github.com/users/SpringCloud","type":"Organization","site_admin":false},"description":":palm_tree: A sample for zuul-swagger2 to test original services","fork":false,"url":"https://api.github.com/repos/SpringCloud/sample-zuul-swagger2","created_at":"2018-06-06T01:22:58Z","updated_at":"2020-06-09T09:35:24Z","pushed_at":"2018-12-24T10:42:51Z","homepage":"","size":125,"stargazers_count":35,"watchers_count":35,"language":"Java","has_issues":true,"has_projects":true,"has_downloads":true,"has_wiki":true,"has_pages":false,"forks_count":22,"archived":false,"disabled":false,"open_issues_count":0,"license":{"key":"apache-2.0","name":"Apache License 2.0","spdx_id":"Apache-2.0","url":"https://api.github.com/licenses/apache-2.0","node_id":"MDc6TGljZW5zZTI="},"forks":22,"open_issues":0,"watchers":35,"default_branch":"master","permissions":{"admin":false,"push":false,"pull":true},"temp_clone_token":"","organization":{"login":"SpringCloud","id":15123112,"node_id":"MDEyOk9yZ2FuaXphdGlvbjE1MTIzMTEy","gravatar_id":"","url":"https://api.github.com/users/SpringCloud","type":"Organization","site_admin":false},"network_count":22,"subscribers_count":6}