{"id":103948659,"node_id":"MDEwOlJlcG9zaXRvcnkxMDM5NDg2NTk=","name":"SpidersMaven","full_name":"youngkuan/SpidersMaven","private":false,"owner":{"login":"youngkuan","id":20515960,"node_id":"MDQ6VXNlcjIwNTE1OTYw","gravatar_id":"","url":"https://api.github.com/users/youngkuan","type":"User","site_admin":false},"description":"爬虫程序：支持爬取问答类网站（Quora/SO/Yahoo Answer/知乎/百度知道等）、百科类网站（百度百科/中英文维基百科等）、博客类网站（CSDN/Twitter等）","fork":false,"url":"https://api.github.com/repos/youngkuan/SpidersMaven","created_at":"2017-09-18T14:19:47Z","updated_at":"2020-06-15T17:04:40Z","pushed_at":"2017-12-04T09:33:26Z","homepage":"","size":161,"stargazers_count":16,"watchers_count":16,"language":"Java","has_issues":false,"has_projects":true,"has_downloads":true,"has_wiki":true,"has_pages":false,"forks_count":9,"archived":false,"disabled":false,"open_issues_count":0,"forks":9,"open_issues":0,"watchers":16,"default_branch":"master","permissions":{"admin":false,"push":false,"pull":true},"temp_clone_token":"","network_count":9,"subscribers_count":1}