{"id":15803421,"node_id":"MDEwOlJlcG9zaXRvcnkxNTgwMzQyMQ==","name":"tiny-spring","full_name":"code4craft/tiny-spring","private":false,"owner":{"login":"code4craft","id":1351884,"node_id":"MDQ6VXNlcjEzNTE4ODQ=","gravatar_id":"","url":"https://api.github.com/users/code4craft","type":"User","site_admin":false},"description":"A tiny IoC container refer to Spring.","fork":false,"url":"https://api.github.com/repos/code4craft/tiny-spring","created_at":"2014-01-10T16:37:57Z","updated_at":"2020-06-25T15:00:22Z","pushed_at":"2019-07-28T10:03:51Z","size":637,"stargazers_count":2794,"watchers_count":2794,"language":"Java","has_issues":true,"has_projects":true,"has_downloads":true,"has_wiki":true,"has_pages":false,"forks_count":1472,"archived":false,"disabled":false,"open_issues_count":20,"license":{"key":"apache-2.0","name":"Apache License 2.0","spdx_id":"Apache-2.0","url":"https://api.github.com/licenses/apache-2.0","node_id":"MDc6TGljZW5zZTI="},"forks":1472,"open_issues":20,"watchers":2794,"default_branch":"master","permissions":{"admin":false,"push":false,"pull":true},"temp_clone_token":"","network_count":1472,"subscribers_count":199}