{"id":38250906,"node_id":"MDEwOlJlcG9zaXRvcnkzODI1MDkwNg==","name":"distiller-CORE","full_name":"ailab-uniud/distiller-CORE","private":false,"owner":{"login":"ailab-uniud","id":13103161,"node_id":"MDEyOk9yZ2FuaXphdGlvbjEzMTAzMTYx","gravatar_id":"","url":"https://api.github.com/users/ailab-uniud","type":"Organization","site_admin":false},"description":"Knowledge extraction framework built with extensibility and multilinguality in mind. ","fork":false,"url":"https://api.github.com/repos/ailab-uniud/distiller-CORE","created_at":"2015-06-29T14:06:06Z","updated_at":"2019-01-22T23:51:07Z","pushed_at":"2017-05-29T14:50:27Z","homepage":"","size":75765,"stargazers_count":9,"watchers_count":9,"language":"Java","has_issues":true,"has_projects":true,"has_downloads":true,"has_wiki":true,"has_pages":false,"forks_count":0,"archived":false,"disabled":false,"open_issues_count":0,"license":{"key":"gpl-2.0","name":"GNU General Public License v2.0","spdx_id":"GPL-2.0","url":"https://api.github.com/licenses/gpl-2.0","node_id":"MDc6TGljZW5zZTg="},"forks":0,"open_issues":0,"watchers":9,"default_branch":"master","permissions":{"admin":false,"push":false,"pull":true},"temp_clone_token":"","organization":{"login":"ailab-uniud","id":13103161,"node_id":"MDEyOk9yZ2FuaXphdGlvbjEzMTAzMTYx","gravatar_id":"","url":"https://api.github.com/users/ailab-uniud","type":"Organization","site_admin":false},"network_count":0,"subscribers_count":6}