{"id":67174321,"node_id":"MDEwOlJlcG9zaXRvcnk2NzE3NDMyMQ==","name":"hashed-wheel-timer","full_name":"Spikhalskiy/hashed-wheel-timer","private":false,"owner":{"login":"Spikhalskiy","id":532108,"node_id":"MDQ6VXNlcjUzMjEwOA==","gravatar_id":"","url":"https://api.github.com/users/Spikhalskiy","type":"User","site_admin":false},"description":"Simple Hashed Wheel Timer implementation","fork":false,"url":"https://api.github.com/repos/Spikhalskiy/hashed-wheel-timer","created_at":"2016-09-01T23:46:16Z","updated_at":"2019-10-24T16:49:08Z","pushed_at":"2016-10-05T14:01:18Z","size":23,"stargazers_count":10,"watchers_count":10,"language":"Java","has_issues":true,"has_projects":true,"has_downloads":true,"has_wiki":true,"has_pages":false,"forks_count":3,"archived":false,"disabled":false,"open_issues_count":0,"license":{"key":"apache-2.0","name":"Apache License 2.0","spdx_id":"Apache-2.0","url":"https://api.github.com/licenses/apache-2.0","node_id":"MDc6TGljZW5zZTI="},"forks":3,"open_issues":0,"watchers":10,"default_branch":"master","permissions":{"admin":false,"push":false,"pull":true},"temp_clone_token":"","network_count":3,"subscribers_count":2}