{"id":86106850,"node_id":"MDEwOlJlcG9zaXRvcnk4NjEwNjg1MA==","name":"helden-software-loader","full_name":"MarkusBauer/helden-software-loader","private":false,"owner":{"login":"MarkusBauer","id":9571253,"node_id":"MDQ6VXNlcjk1NzEyNTM=","gravatar_id":"","url":"https://api.github.com/users/MarkusBauer","type":"User","site_admin":false},"description":"A plugin for \"Helden-Software\", a character manager for the german RPG \"Das Schwarze Auge\". This plugin allows users to add new content to the program. ","fork":false,"url":"https://api.github.com/repos/MarkusBauer/helden-software-loader","created_at":"2017-03-24T20:12:41Z","updated_at":"2020-05-17T21:21:41Z","pushed_at":"2020-05-19T17:31:12Z","size":136,"stargazers_count":5,"watchers_count":5,"language":"Java","has_issues":true,"has_projects":true,"has_downloads":true,"has_wiki":true,"has_pages":false,"forks_count":2,"archived":false,"disabled":false,"open_issues_count":0,"forks":2,"open_issues":0,"watchers":5,"default_branch":"master","permissions":{"admin":false,"push":false,"pull":true},"temp_clone_token":"","network_count":2,"subscribers_count":3}