{"id":7889658,"node_id":"MDEwOlJlcG9zaXRvcnk3ODg5NjU4","name":"MySample","full_name":"sam85/MySample","private":false,"owner":{"login":"sam85","id":3415559,"node_id":"MDQ6VXNlcjM0MTU1NTk=","gravatar_id":"","url":"https://api.github.com/users/sam85","type":"User","site_admin":false},"description":"Sample Project","fork":false,"url":"https://api.github.com/repos/sam85/MySample","created_at":"2013-01-29T10:03:17Z","updated_at":"2016-03-19T20:32:39Z","pushed_at":"2013-04-09T06:56:41Z","size":29151,"stargazers_count":13,"watchers_count":13,"language":"Java","has_issues":true,"has_projects":true,"has_downloads":true,"has_wiki":true,"has_pages":true,"forks_count":18,"archived":false,"disabled":false,"open_issues_count":0,"forks":18,"open_issues":0,"watchers":13,"default_branch":"master","permissions":{"admin":false,"push":false,"pull":true},"temp_clone_token":"","network_count":18,"subscribers_count":4}