{"id":92861495,"node_id":"MDEwOlJlcG9zaXRvcnk5Mjg2MTQ5NQ==","name":"kafka-javaee-concurrency-utilities","full_name":"abhirockzz/kafka-javaee-concurrency-utilities","private":false,"owner":{"login":"abhirockzz","id":6301594,"node_id":"MDQ6VXNlcjYzMDE1OTQ=","gravatar_id":"","url":"https://api.github.com/users/abhirockzz","type":"User","site_admin":false},"description":"kafEEne: Kafka + Java EE Concurrency Utilities","fork":false,"url":"https://api.github.com/repos/abhirockzz/kafka-javaee-concurrency-utilities","created_at":"2017-05-30T18:01:48Z","updated_at":"2019-05-01T07:50:04Z","pushed_at":"2017-06-01T13:34:52Z","homepage":"https://abhirockzz.wordpress.com/2017/06/01/kafeene-2-kafka-concurrency-utilities/","size":10,"stargazers_count":6,"watchers_count":6,"language":"Java","has_issues":true,"has_projects":true,"has_downloads":true,"has_wiki":true,"has_pages":false,"forks_count":3,"archived":false,"disabled":false,"open_issues_count":0,"license":{"key":"mit","name":"MIT License","spdx_id":"MIT","url":"https://api.github.com/licenses/mit","node_id":"MDc6TGljZW5zZTEz"},"forks":3,"open_issues":0,"watchers":6,"default_branch":"master","permissions":{"admin":false,"push":false,"pull":true},"temp_clone_token":"","network_count":3,"subscribers_count":1}