{"id":68070123,"node_id":"MDEwOlJlcG9zaXRvcnk2ODA3MDEyMw==","name":"WebIDE-Backend","full_name":"Coding/WebIDE-Backend","private":false,"owner":{"login":"Coding","id":13644380,"node_id":"MDEyOk9yZ2FuaXphdGlvbjEzNjQ0Mzgw","gravatar_id":"","url":"https://api.github.com/users/Coding","type":"Organization","site_admin":false},"description":"WebIDE 后端项目","fork":false,"url":"https://api.github.com/repos/Coding/WebIDE-Backend","created_at":"2016-09-13T03:17:26Z","updated_at":"2020-06-11T09:16:13Z","pushed_at":"2017-12-01T01:30:15Z","homepage":"https://ide.coding.net/community","size":1881,"stargazers_count":208,"watchers_count":208,"language":"Java","has_issues":true,"has_projects":true,"has_downloads":true,"has_wiki":true,"has_pages":false,"forks_count":115,"archived":false,"disabled":false,"open_issues_count":1,"license":{"key":"bsd-3-clause","name":"BSD 3-Clause \"New\" or \"Revised\" License","spdx_id":"BSD-3-Clause","url":"https://api.github.com/licenses/bsd-3-clause","node_id":"MDc6TGljZW5zZTU="},"forks":115,"open_issues":1,"watchers":208,"default_branch":"master","permissions":{"admin":false,"push":false,"pull":true},"temp_clone_token":"","organization":{"login":"Coding","id":13644380,"node_id":"MDEyOk9yZ2FuaXphdGlvbjEzNjQ0Mzgw","gravatar_id":"","url":"https://api.github.com/users/Coding","type":"Organization","site_admin":false},"network_count":115,"subscribers_count":29}