{"id":56300987,"node_id":"MDEwOlJlcG9zaXRvcnk1NjMwMDk4Nw==","name":"spring-rabbitmq","full_name":"michaellihs/spring-rabbitmq","private":false,"owner":{"login":"michaellihs","id":575011,"node_id":"MDQ6VXNlcjU3NTAxMQ==","gravatar_id":"","url":"https://api.github.com/users/michaellihs","type":"User","site_admin":false},"description":"Sample application for Spring Boot and RabbitMQ","fork":false,"url":"https://api.github.com/repos/michaellihs/spring-rabbitmq","created_at":"2016-04-15T07:39:39Z","updated_at":"2019-09-13T20:50:13Z","pushed_at":"2016-04-19T09:59:17Z","size":160,"stargazers_count":7,"watchers_count":7,"language":"Java","has_issues":true,"has_projects":true,"has_downloads":true,"has_wiki":true,"has_pages":false,"forks_count":6,"archived":false,"disabled":false,"open_issues_count":0,"forks":6,"open_issues":0,"watchers":7,"default_branch":"master","permissions":{"admin":false,"push":false,"pull":true},"temp_clone_token":"","network_count":6,"subscribers_count":2}