{"id":47183095,"node_id":"MDEwOlJlcG9zaXRvcnk0NzE4MzA5NQ==","name":"voucher-code-generator-java","full_name":"voucherifyio/voucher-code-generator-java","private":false,"owner":{"login":"voucherifyio","id":19346225,"node_id":"MDEyOk9yZ2FuaXphdGlvbjE5MzQ2MjI1","gravatar_id":"","url":"https://api.github.com/users/voucherifyio","type":"Organization","site_admin":false},"fork":false,"url":"https://api.github.com/repos/voucherifyio/voucher-code-generator-java","created_at":"2015-12-01T10:44:44Z","updated_at":"2020-05-08T10:11:25Z","pushed_at":"2017-10-24T14:03:22Z","size":6,"stargazers_count":18,"watchers_count":18,"language":"Java","has_issues":true,"has_projects":true,"has_downloads":true,"has_wiki":true,"has_pages":false,"forks_count":8,"archived":false,"disabled":false,"open_issues_count":0,"license":{"key":"mit","name":"MIT License","spdx_id":"MIT","url":"https://api.github.com/licenses/mit","node_id":"MDc6TGljZW5zZTEz"},"forks":8,"open_issues":0,"watchers":18,"default_branch":"master","permissions":{"admin":false,"push":false,"pull":true},"temp_clone_token":"","organization":{"login":"voucherifyio","id":19346225,"node_id":"MDEyOk9yZ2FuaXphdGlvbjE5MzQ2MjI1","gravatar_id":"","url":"https://api.github.com/users/voucherifyio","type":"Organization","site_admin":false},"network_count":8,"subscribers_count":17}