{"id":88242458,"node_id":"MDEwOlJlcG9zaXRvcnk4ODI0MjQ1OA==","name":"sso","full_name":"mazh1992/sso","private":false,"owner":{"login":"mazh1992","id":14176235,"node_id":"MDQ6VXNlcjE0MTc2MjM1","gravatar_id":"","url":"https://api.github.com/users/mazh1992","type":"User","site_admin":false},"description":"单点登录","fork":false,"url":"https://api.github.com/repos/mazh1992/sso","created_at":"2017-04-14T07:04:34Z","updated_at":"2020-04-18T12:11:47Z","pushed_at":"2017-04-14T07:18:00Z","size":848,"stargazers_count":8,"watchers_count":8,"language":"Java","has_issues":true,"has_projects":true,"has_downloads":true,"has_wiki":true,"has_pages":false,"forks_count":6,"archived":false,"disabled":false,"open_issues_count":1,"forks":6,"open_issues":1,"watchers":8,"default_branch":"master","permissions":{"admin":false,"push":false,"pull":true},"temp_clone_token":"","network_count":6,"subscribers_count":1}