{"id":144974321,"node_id":"MDEwOlJlcG9zaXRvcnkxNDQ5NzQzMjE=","name":"robot","full_name":"ghwswywps/robot","private":false,"owner":{"login":"ghwswywps","id":18697235,"node_id":"MDQ6VXNlcjE4Njk3MjM1","gravatar_id":"","url":"https://api.github.com/users/ghwswywps","type":"User","site_admin":false},"description":"DingTalk Chatbot","fork":false,"url":"https://api.github.com/repos/ghwswywps/robot","created_at":"2018-08-16T10:40:42Z","updated_at":"2020-05-29T06:48:33Z","pushed_at":"2020-04-22T11:34:07Z","homepage":"https://github.com/ghwswywps/robot/wiki/ChatRobot","size":398,"stargazers_count":24,"watchers_count":24,"language":"Java","has_issues":true,"has_projects":true,"has_downloads":true,"has_wiki":true,"has_pages":false,"forks_count":7,"archived":false,"disabled":false,"open_issues_count":0,"forks":7,"open_issues":0,"watchers":24,"default_branch":"master","permissions":{"admin":false,"push":false,"pull":true},"temp_clone_token":"","network_count":7,"subscribers_count":2}