{"id":112095605,"node_id":"MDEwOlJlcG9zaXRvcnkxMTIwOTU2MDU=","name":"quant-backend","full_name":"irusist/quant-backend","private":false,"owner":{"login":"irusist","id":2133542,"node_id":"MDQ6VXNlcjIxMzM1NDI=","gravatar_id":"","url":"https://api.github.com/users/irusist","type":"User","site_admin":false},"description":"指数估值计算，查询","fork":false,"url":"https://api.github.com/repos/irusist/quant-backend","created_at":"2017-11-26T15:51:35Z","updated_at":"2020-05-10T04:27:36Z","pushed_at":"2018-02-08T15:00:01Z","homepage":"http://47.100.121.74:8080/","size":74,"stargazers_count":5,"watchers_count":5,"language":"Java","has_issues":true,"has_projects":true,"has_downloads":true,"has_wiki":true,"has_pages":false,"forks_count":0,"archived":false,"disabled":false,"open_issues_count":0,"forks":0,"open_issues":0,"watchers":5,"default_branch":"master","permissions":{"admin":false,"push":false,"pull":true},"temp_clone_token":"","network_count":0,"subscribers_count":1}