{"id":96219836,"node_id":"MDEwOlJlcG9zaXRvcnk5NjIxOTgzNg==","name":"nexus3-keycloak-plugin","full_name":"flytreeleft/nexus3-keycloak-plugin","private":false,"owner":{"login":"flytreeleft","id":1321315,"node_id":"MDQ6VXNlcjEzMjEzMTU=","gravatar_id":"","url":"https://api.github.com/users/flytreeleft","type":"User","site_admin":false},"description":"Sonatype Nexus plugin for Keycloak integration","fork":false,"url":"https://api.github.com/repos/flytreeleft/nexus3-keycloak-plugin","created_at":"2017-07-04T13:14:03Z","updated_at":"2020-06-18T12:46:47Z","pushed_at":"2020-04-11T10:02:15Z","size":945,"stargazers_count":51,"watchers_count":51,"language":"Java","has_issues":true,"has_projects":true,"has_downloads":true,"has_wiki":true,"has_pages":false,"forks_count":28,"archived":false,"disabled":false,"open_issues_count":3,"license":{"key":"apache-2.0","name":"Apache License 2.0","spdx_id":"Apache-2.0","url":"https://api.github.com/licenses/apache-2.0","node_id":"MDc6TGljZW5zZTI="},"forks":28,"open_issues":3,"watchers":51,"default_branch":"master","permissions":{"admin":false,"push":false,"pull":true},"temp_clone_token":"","network_count":28,"subscribers_count":5}