{"id":160678066,"node_id":"MDEwOlJlcG9zaXRvcnkxNjA2NzgwNjY=","name":"S7Server491","full_name":"jessefjxm/S7Server491","private":false,"owner":{"login":"jessefjxm","id":1498592,"node_id":"MDQ6VXNlcjE0OTg1OTI=","gravatar_id":"","url":"https://api.github.com/users/jessefjxm","type":"User","site_admin":false},"description":"黑色沙漠491服务端","fork":false,"url":"https://api.github.com/repos/jessefjxm/S7Server491","created_at":"2018-12-06T13:23:14Z","updated_at":"2019-12-15T16:34:47Z","pushed_at":"2018-12-07T15:44:54Z","size":22201,"stargazers_count":6,"watchers_count":6,"language":"Java","has_issues":true,"has_projects":true,"has_downloads":true,"has_wiki":true,"has_pages":false,"forks_count":9,"archived":false,"disabled":false,"open_issues_count":1,"license":{"key":"apache-2.0","name":"Apache License 2.0","spdx_id":"Apache-2.0","url":"https://api.github.com/licenses/apache-2.0","node_id":"MDc6TGljZW5zZTI="},"forks":9,"open_issues":1,"watchers":6,"default_branch":"master","permissions":{"admin":false,"push":false,"pull":true},"temp_clone_token":"","network_count":9,"subscribers_count":1}