{"id":9124858,"node_id":"MDEwOlJlcG9zaXRvcnk5MTI0ODU4","name":"squirrel","full_name":"hekailiang/squirrel","private":false,"owner":{"login":"hekailiang","id":986219,"node_id":"MDQ6VXNlcjk4NjIxOQ==","gravatar_id":"","url":"https://api.github.com/users/hekailiang","type":"User","site_admin":false},"description":"squirrel-foundation is a State Machine library, which provided a lightweight, easy use, type safe and programmable state machine implementation for Java.","fork":false,"url":"https://api.github.com/repos/hekailiang/squirrel","created_at":"2013-03-31T02:24:18Z","updated_at":"2020-06-24T05:46:47Z","pushed_at":"2020-06-24T04:43:49Z","homepage":"http://hekailiang.github.io/squirrel/","size":3087,"stargazers_count":1442,"watchers_count":1442,"language":"Java","has_issues":true,"has_projects":true,"has_downloads":true,"has_wiki":true,"has_pages":true,"forks_count":392,"archived":false,"disabled":false,"open_issues_count":50,"license":{"key":"other","name":"Other","spdx_id":"NOASSERTION","node_id":"MDc6TGljZW5zZTA="},"forks":392,"open_issues":50,"watchers":1442,"default_branch":"master","permissions":{"admin":false,"push":false,"pull":true},"temp_clone_token":"","network_count":392,"subscribers_count":145}