{"id":63939253,"node_id":"MDEwOlJlcG9zaXRvcnk2MzkzOTI1Mw==","name":"code-hidding-plugin","full_name":"keyhunter/code-hidding-plugin","private":false,"owner":{"login":"keyhunter","id":7654175,"node_id":"MDQ6VXNlcjc2NTQxNzU=","gravatar_id":"","url":"https://api.github.com/users/keyhunter","type":"User","site_admin":false},"description":"Code hidding-plugin.在proguard-maven-plugin的基础上修改而来，可以在项目构建过的时候把代码混淆，支持打成jar包和war包。 基本支持Proguard的所有功能。","fork":false,"url":"https://api.github.com/repos/keyhunter/code-hidding-plugin","created_at":"2016-07-22T08:57:50Z","updated_at":"2019-12-29T14:42:12Z","pushed_at":"2017-02-24T09:58:40Z","homepage":"http://blog.csdn.net/connect_me/article/details/51320913","size":34,"stargazers_count":32,"watchers_count":32,"language":"Java","has_issues":true,"has_projects":true,"has_downloads":true,"has_wiki":true,"has_pages":false,"forks_count":35,"archived":false,"disabled":false,"open_issues_count":0,"license":{"key":"lgpl-2.1","name":"GNU Lesser General Public License v2.1","spdx_id":"LGPL-2.1","url":"https://api.github.com/licenses/lgpl-2.1","node_id":"MDc6TGljZW5zZTEx"},"forks":35,"open_issues":0,"watchers":32,"default_branch":"master","permissions":{"admin":false,"push":false,"pull":true},"temp_clone_token":"","network_count":35,"subscribers_count":14}