{"id":9680727,"node_id":"MDEwOlJlcG9zaXRvcnk5NjgwNzI3","name":"SolrTextTagger","full_name":"OpenSextant/SolrTextTagger","private":false,"owner":{"login":"OpenSextant","id":4237411,"node_id":"MDEyOk9yZ2FuaXphdGlvbjQyMzc0MTE=","gravatar_id":"","url":"https://api.github.com/users/OpenSextant","type":"Organization","site_admin":false},"description":"A text tagger based on Lucene / Solr, using FST technology","fork":false,"url":"https://api.github.com/repos/OpenSextant/SolrTextTagger","created_at":"2013-04-25T20:31:25Z","updated_at":"2020-03-30T15:32:16Z","pushed_at":"2020-02-12T19:34:14Z","size":393,"stargazers_count":161,"watchers_count":161,"language":"Java","has_issues":true,"has_projects":true,"has_downloads":true,"has_wiki":false,"has_pages":false,"forks_count":35,"archived":false,"disabled":false,"open_issues_count":19,"license":{"key":"apache-2.0","name":"Apache License 2.0","spdx_id":"Apache-2.0","url":"https://api.github.com/licenses/apache-2.0","node_id":"MDc6TGljZW5zZTI="},"forks":35,"open_issues":19,"watchers":161,"default_branch":"master","permissions":{"admin":false,"push":false,"pull":true},"temp_clone_token":"","organization":{"login":"OpenSextant","id":4237411,"node_id":"MDEyOk9yZ2FuaXphdGlvbjQyMzc0MTE=","gravatar_id":"","url":"https://api.github.com/users/OpenSextant","type":"Organization","site_admin":false},"network_count":35,"subscribers_count":30}