{"id":108597170,"node_id":"MDEwOlJlcG9zaXRvcnkxMDg1OTcxNzA=","name":"bazel-generator-plugin","full_name":"redfin/bazel-generator-plugin","private":false,"owner":{"login":"redfin","id":6288468,"node_id":"MDEyOk9yZ2FuaXphdGlvbjYyODg0Njg=","gravatar_id":"","url":"https://api.github.com/users/redfin","type":"Organization","site_admin":false},"fork":false,"url":"https://api.github.com/repos/redfin/bazel-generator-plugin","created_at":"2017-10-27T21:25:00Z","updated_at":"2019-07-17T20:24:06Z","pushed_at":"2017-10-27T21:43:46Z","size":5,"stargazers_count":11,"watchers_count":11,"language":"Java","has_issues":true,"has_projects":true,"has_downloads":true,"has_wiki":false,"has_pages":false,"forks_count":2,"archived":false,"disabled":false,"open_issues_count":3,"forks":2,"open_issues":3,"watchers":11,"default_branch":"master","permissions":{"admin":false,"push":false,"pull":true},"temp_clone_token":"","organization":{"login":"redfin","id":6288468,"node_id":"MDEyOk9yZ2FuaXphdGlvbjYyODg0Njg=","gravatar_id":"","url":"https://api.github.com/users/redfin","type":"Organization","site_admin":false},"network_count":2,"subscribers_count":26}