{"id":73566900,"node_id":"MDEwOlJlcG9zaXRvcnk3MzU2NjkwMA==","name":"mobi-api4java","full_name":"rrauschenbach/mobi-api4java","private":false,"owner":{"login":"rrauschenbach","id":23196856,"node_id":"MDQ6VXNlcjIzMTk2ODU2","gravatar_id":"","url":"https://api.github.com/users/rrauschenbach","type":"User","site_admin":false},"description":"mobi-api4java is a java api to read, write and modify mobipocket (.mobi, .azw) files.","fork":false,"url":"https://api.github.com/repos/rrauschenbach/mobi-api4java","created_at":"2016-11-12T17:15:49Z","updated_at":"2020-06-04T12:09:20Z","pushed_at":"2017-02-26T14:39:15Z","homepage":"","size":975,"stargazers_count":14,"watchers_count":14,"language":"Java","has_issues":true,"has_projects":true,"has_downloads":true,"has_wiki":true,"has_pages":false,"forks_count":4,"archived":false,"disabled":false,"open_issues_count":0,"license":{"key":"apache-2.0","name":"Apache License 2.0","spdx_id":"Apache-2.0","url":"https://api.github.com/licenses/apache-2.0","node_id":"MDc6TGljZW5zZTI="},"forks":4,"open_issues":0,"watchers":14,"default_branch":"master","permissions":{"admin":false,"push":false,"pull":true},"temp_clone_token":"","network_count":4,"subscribers_count":1}