{"id":121907769,"node_id":"MDEwOlJlcG9zaXRvcnkxMjE5MDc3Njk=","name":"Campus-Information-Management-System","full_name":"tcsx/Campus-Information-Management-System","private":false,"owner":{"login":"tcsx","id":17824318,"node_id":"MDQ6VXNlcjE3ODI0MzE4","gravatar_id":"","url":"https://api.github.com/users/tcsx","type":"User","site_admin":false},"fork":false,"url":"https://api.github.com/repos/tcsx/Campus-Information-Management-System","created_at":"2018-02-18T01:24:35Z","updated_at":"2018-09-27T06:27:22Z","pushed_at":"2018-09-26T21:15:42Z","size":79,"stargazers_count":7,"watchers_count":7,"language":"Java","has_issues":true,"has_projects":true,"has_downloads":true,"has_wiki":true,"has_pages":false,"forks_count":0,"archived":false,"disabled":false,"open_issues_count":0,"forks":0,"open_issues":0,"watchers":7,"default_branch":"master","permissions":{"admin":false,"push":false,"pull":true},"temp_clone_token":"","network_count":0,"subscribers_count":1}