{"id":107735816,"node_id":"MDEwOlJlcG9zaXRvcnkxMDc3MzU4MTY=","name":"bsonpatch","full_name":"eBay/bsonpatch","private":false,"owner":{"login":"eBay","id":3639281,"node_id":"MDEyOk9yZ2FuaXphdGlvbjM2MzkyODE=","gravatar_id":"","url":"https://api.github.com/users/eBay","type":"Organization","site_admin":false},"description":"A BSON implementation of RFC 6902 to compute the difference between two BSON documents","fork":false,"url":"https://api.github.com/repos/eBay/bsonpatch","created_at":"2017-10-20T23:29:40Z","updated_at":"2020-06-16T03:47:24Z","pushed_at":"2019-11-11T21:10:55Z","homepage":"","size":207,"stargazers_count":18,"watchers_count":18,"language":"Java","has_issues":true,"has_projects":true,"has_downloads":true,"has_wiki":true,"has_pages":false,"forks_count":7,"archived":false,"disabled":false,"open_issues_count":0,"license":{"key":"apache-2.0","name":"Apache License 2.0","spdx_id":"Apache-2.0","url":"https://api.github.com/licenses/apache-2.0","node_id":"MDc6TGljZW5zZTI="},"forks":7,"open_issues":0,"watchers":18,"default_branch":"master","permissions":{"admin":false,"push":false,"pull":true},"temp_clone_token":"","organization":{"login":"eBay","id":3639281,"node_id":"MDEyOk9yZ2FuaXphdGlvbjM2MzkyODE=","gravatar_id":"","url":"https://api.github.com/users/eBay","type":"Organization","site_admin":false},"network_count":7,"subscribers_count":5}