{"id":50037913,"node_id":"MDEwOlJlcG9zaXRvcnk1MDAzNzkxMw==","name":"wro4j-spring-boot-starter","full_name":"michael-simons/wro4j-spring-boot-starter","private":false,"owner":{"login":"michael-simons","id":526383,"node_id":"MDQ6VXNlcjUyNjM4Mw==","gravatar_id":"","url":"https://api.github.com/users/michael-simons","type":"User","site_admin":false},"description":"A Spring Boot starter and auto-configuration for wro4j (http://alexo.github.io/wro4j/)","fork":false,"url":"https://api.github.com/repos/michael-simons/wro4j-spring-boot-starter","created_at":"2016-01-20T15:09:57Z","updated_at":"2020-06-16T16:51:18Z","pushed_at":"2020-06-12T04:50:43Z","homepage":"","size":302,"stargazers_count":55,"watchers_count":55,"language":"Java","has_issues":true,"has_projects":true,"has_downloads":true,"has_wiki":true,"has_pages":false,"forks_count":2,"archived":false,"disabled":false,"open_issues_count":4,"license":{"key":"apache-2.0","name":"Apache License 2.0","spdx_id":"Apache-2.0","url":"https://api.github.com/licenses/apache-2.0","node_id":"MDc6TGljZW5zZTI="},"forks":2,"open_issues":4,"watchers":55,"default_branch":"master","permissions":{"admin":false,"push":false,"pull":true},"temp_clone_token":"","network_count":2,"subscribers_count":5}