{"id":144588701,"node_id":"MDEwOlJlcG9zaXRvcnkxNDQ1ODg3MDE=","name":"Java-Audio-Wave-Spectrum-API","full_name":"goxr3plus/Java-Audio-Wave-Spectrum-API","private":false,"owner":{"login":"goxr3plus","id":20374208,"node_id":"MDQ6VXNlcjIwMzc0MjA4","gravatar_id":"","url":"https://api.github.com/users/goxr3plus","type":"User","site_admin":false},"description":"Create Wave Spectrums from any Audio File using this API , written in JavaFX","fork":false,"url":"https://api.github.com/repos/goxr3plus/Java-Audio-Wave-Spectrum-API","created_at":"2018-08-13T14:09:34Z","updated_at":"2020-06-17T01:35:59Z","pushed_at":"2018-08-27T21:31:00Z","homepage":"","size":6480,"stargazers_count":17,"watchers_count":17,"language":"Java","has_issues":true,"has_projects":true,"has_downloads":true,"has_wiki":true,"has_pages":false,"forks_count":7,"archived":false,"disabled":false,"open_issues_count":0,"license":{"key":"lgpl-3.0","name":"GNU Lesser General Public License v3.0","spdx_id":"LGPL-3.0","url":"https://api.github.com/licenses/lgpl-3.0","node_id":"MDc6TGljZW5zZTEy"},"forks":7,"open_issues":0,"watchers":17,"default_branch":"master","permissions":{"admin":false,"push":false,"pull":true},"temp_clone_token":"","network_count":7,"subscribers_count":2}