{"id":90409457,"node_id":"MDEwOlJlcG9zaXRvcnk5MDQwOTQ1Nw==","name":"dependency-scope-maven-plugin","full_name":"HubSpot/dependency-scope-maven-plugin","private":false,"owner":{"login":"HubSpot","id":326419,"node_id":"MDEyOk9yZ2FuaXphdGlvbjMyNjQxOQ==","gravatar_id":"","url":"https://api.github.com/users/HubSpot","type":"Organization","site_admin":false},"fork":false,"url":"https://api.github.com/repos/HubSpot/dependency-scope-maven-plugin","created_at":"2017-05-05T19:22:46Z","updated_at":"2020-04-20T21:05:18Z","pushed_at":"2020-04-20T21:05:16Z","size":53,"stargazers_count":7,"watchers_count":7,"language":"Java","has_issues":true,"has_projects":true,"has_downloads":true,"has_wiki":true,"has_pages":false,"forks_count":4,"archived":false,"disabled":false,"open_issues_count":0,"license":{"key":"apache-2.0","name":"Apache License 2.0","spdx_id":"Apache-2.0","url":"https://api.github.com/licenses/apache-2.0","node_id":"MDc6TGljZW5zZTI="},"forks":4,"open_issues":0,"watchers":7,"default_branch":"master","permissions":{"admin":false,"push":false,"pull":true},"temp_clone_token":"","organization":{"login":"HubSpot","id":326419,"node_id":"MDEyOk9yZ2FuaXphdGlvbjMyNjQxOQ==","gravatar_id":"","url":"https://api.github.com/users/HubSpot","type":"Organization","site_admin":false},"network_count":4,"subscribers_count":3}