{"id":31306050,"node_id":"MDEwOlJlcG9zaXRvcnkzMTMwNjA1MA==","name":"spooet","full_name":"SpoonLabs/spooet","private":false,"owner":{"login":"SpoonLabs","id":8879174,"node_id":"MDEyOk9yZ2FuaXphdGlvbjg4NzkxNzQ=","gravatar_id":"","url":"https://api.github.com/users/SpoonLabs","type":"Organization","site_admin":false},"description":"a prototype Spoon pretty-printer implemented with JavaPoet","fork":false,"url":"https://api.github.com/repos/SpoonLabs/spooet","created_at":"2015-02-25T09:23:19Z","updated_at":"2020-01-09T03:24:46Z","pushed_at":"2018-04-18T13:53:49Z","homepage":"","size":28,"stargazers_count":9,"watchers_count":9,"language":"Java","has_issues":true,"has_projects":true,"has_downloads":true,"has_wiki":true,"has_pages":false,"forks_count":0,"archived":false,"disabled":false,"open_issues_count":0,"forks":0,"open_issues":0,"watchers":9,"default_branch":"master","permissions":{"admin":false,"push":false,"pull":true},"temp_clone_token":"","organization":{"login":"SpoonLabs","id":8879174,"node_id":"MDEyOk9yZ2FuaXphdGlvbjg4NzkxNzQ=","gravatar_id":"","url":"https://api.github.com/users/SpoonLabs","type":"Organization","site_admin":false},"network_count":0,"subscribers_count":1}