{"id":7017266,"node_id":"MDEwOlJlcG9zaXRvcnk3MDE3MjY2","name":"Umigon","full_name":"seinecle/Umigon","private":false,"owner":{"login":"seinecle","id":1244100,"node_id":"MDQ6VXNlcjEyNDQxMDA=","gravatar_id":"","url":"https://api.github.com/users/seinecle","type":"User","site_admin":false},"description":"Semantic analysis for Twitter","fork":false,"url":"https://api.github.com/repos/seinecle/Umigon","created_at":"2012-12-05T12:44:31Z","updated_at":"2019-04-23T01:55:46Z","pushed_at":"2017-02-01T10:48:03Z","homepage":"http://www.umigon.com","size":1872,"stargazers_count":25,"watchers_count":25,"language":"Java","has_issues":true,"has_projects":true,"has_downloads":true,"has_wiki":true,"has_pages":false,"forks_count":11,"archived":false,"disabled":false,"open_issues_count":0,"forks":11,"open_issues":0,"watchers":25,"default_branch":"Umigon2.0","permissions":{"admin":false,"push":false,"pull":true},"temp_clone_token":"","network_count":11,"subscribers_count":8}