{"id":30764336,"node_id":"MDEwOlJlcG9zaXRvcnkzMDc2NDMzNg==","name":"simplu3D-rules","full_name":"SimPLU3D/simplu3D-rules","private":false,"owner":{"login":"SimPLU3D","id":36670327,"node_id":"MDEyOk9yZ2FuaXphdGlvbjM2NjcwMzI3","gravatar_id":"","url":"https://api.github.com/users/SimPLU3D","type":"Organization","site_admin":false},"description":"A library to manage local urban regulations.","fork":false,"url":"https://api.github.com/repos/SimPLU3D/simplu3D-rules","created_at":"2015-02-13T16:16:47Z","updated_at":"2019-03-05T11:05:40Z","pushed_at":"2019-03-05T11:05:39Z","size":13647,"stargazers_count":6,"watchers_count":6,"language":"Java","has_issues":true,"has_projects":true,"has_downloads":true,"has_wiki":true,"has_pages":true,"forks_count":0,"archived":false,"disabled":false,"open_issues_count":3,"license":{"key":"other","name":"Other","spdx_id":"NOASSERTION","node_id":"MDc6TGljZW5zZTA="},"forks":0,"open_issues":3,"watchers":6,"default_branch":"master","permissions":{"admin":false,"push":false,"pull":true},"temp_clone_token":"","organization":{"login":"SimPLU3D","id":36670327,"node_id":"MDEyOk9yZ2FuaXphdGlvbjM2NjcwMzI3","gravatar_id":"","url":"https://api.github.com/users/SimPLU3D","type":"Organization","site_admin":false},"network_count":0,"subscribers_count":12}