{"id":7483144,"node_id":"MDEwOlJlcG9zaXRvcnk3NDgzMTQ0","name":"jedis_failover","full_name":"officedrop/jedis_failover","private":false,"owner":{"login":"officedrop","id":366458,"node_id":"MDEyOk9yZ2FuaXphdGlvbjM2NjQ1OA==","gravatar_id":"","url":"https://api.github.com/users/officedrop","type":"Organization","site_admin":false},"description":"Failover solution using the Jedis Redis client.","fork":false,"url":"https://api.github.com/repos/officedrop/jedis_failover","created_at":"2013-01-07T13:53:19Z","updated_at":"2018-05-21T05:12:01Z","pushed_at":"2014-03-07T05:04:48Z","size":337,"stargazers_count":32,"watchers_count":32,"language":"Java","has_issues":true,"has_projects":true,"has_downloads":true,"has_wiki":true,"has_pages":false,"forks_count":18,"archived":false,"disabled":false,"open_issues_count":0,"license":{"key":"mit","name":"MIT License","spdx_id":"MIT","url":"https://api.github.com/licenses/mit","node_id":"MDc6TGljZW5zZTEz"},"forks":18,"open_issues":0,"watchers":32,"default_branch":"master","permissions":{"admin":false,"push":false,"pull":true},"temp_clone_token":"","organization":{"login":"officedrop","id":366458,"node_id":"MDEyOk9yZ2FuaXphdGlvbjM2NjQ1OA==","gravatar_id":"","url":"https://api.github.com/users/officedrop","type":"Organization","site_admin":false},"network_count":18,"subscribers_count":7}