{"id":63406754,"node_id":"MDEwOlJlcG9zaXRvcnk2MzQwNjc1NA==","name":"disconfDemo","full_name":"kazaff/disconfDemo","private":false,"owner":{"login":"kazaff","id":801787,"node_id":"MDQ6VXNlcjgwMTc4Nw==","gravatar_id":"","url":"https://api.github.com/users/kazaff","type":"User","site_admin":false},"description":"disconf+spring boot+mybatis","fork":false,"url":"https://api.github.com/repos/kazaff/disconfDemo","created_at":"2016-07-15T08:50:29Z","updated_at":"2019-04-22T23:29:00Z","pushed_at":"2016-07-15T09:05:48Z","size":18,"stargazers_count":5,"watchers_count":5,"language":"Java","has_issues":true,"has_projects":true,"has_downloads":true,"has_wiki":true,"has_pages":false,"forks_count":3,"archived":false,"disabled":false,"open_issues_count":0,"forks":3,"open_issues":0,"watchers":5,"default_branch":"master","permissions":{"admin":false,"push":false,"pull":true},"temp_clone_token":"","network_count":3,"subscribers_count":2}