{"id":37990634,"node_id":"MDEwOlJlcG9zaXRvcnkzNzk5MDYzNA==","name":"tomcatembedded","full_name":"danjee/tomcatembedded","private":false,"owner":{"login":"danjee","id":3084216,"node_id":"MDQ6VXNlcjMwODQyMTY=","gravatar_id":"","url":"https://api.github.com/users/danjee","type":"User","site_admin":false},"description":"Embedded tomcat","fork":false,"url":"https://api.github.com/repos/danjee/tomcatembedded","created_at":"2015-06-24T14:45:36Z","updated_at":"2019-06-10T15:56:26Z","pushed_at":"2015-06-24T14:46:19Z","size":120,"stargazers_count":5,"watchers_count":5,"language":"Java","has_issues":true,"has_projects":true,"has_downloads":true,"has_wiki":true,"has_pages":false,"forks_count":0,"archived":false,"disabled":false,"open_issues_count":0,"forks":0,"open_issues":0,"watchers":5,"default_branch":"master","permissions":{"admin":false,"push":false,"pull":true},"temp_clone_token":"","network_count":0,"subscribers_count":2}