{"id":34098112,"node_id":"MDEwOlJlcG9zaXRvcnkzNDA5ODExMg==","name":"ZKConfig","full_name":"QuanZhong/ZKConfig","private":false,"owner":{"login":"QuanZhong","id":8435710,"node_id":"MDQ6VXNlcjg0MzU3MTA=","gravatar_id":"","url":"https://api.github.com/users/QuanZhong","type":"User","site_admin":false},"description":"ZkConfig是为zookeeper开发的配置服务工具包，能与现有的Java系统进行良好的集成，也可以使用与非java系统以独立进程运行。提供与spring进行集成的插件。采用注解方式对需要动态更新的内存数据对象进行标注。 ZkConfig用于解决在系统集群中配置文件的实时同步。当任意一台服务器配置文件发生变化的时候，所有集群服务器配置文件实现同步更新，并且在不启动web容器的情况下，实现内存配置对象的实时更新。 目前支持所有种类配置文件的同步更新，仅支持扩展名为.properties与.cfg结尾的健值对文件格式的内存数据对象实时同步。其余配置文件仅支持磁盘数据同步。","fork":false,"url":"https://api.github.com/repos/QuanZhong/ZKConfig","created_at":"2015-04-17T05:22:12Z","updated_at":"2020-01-09T15:56:11Z","pushed_at":"2015-04-17T05:43:15Z","size":450,"stargazers_count":22,"watchers_count":22,"language":"Java","has_issues":true,"has_projects":true,"has_downloads":true,"has_wiki":true,"has_pages":false,"forks_count":29,"archived":false,"disabled":false,"open_issues_count":0,"forks":29,"open_issues":0,"watchers":22,"default_branch":"master","permissions":{"admin":false,"push":false,"pull":true},"temp_clone_token":"","network_count":29,"subscribers_count":10}