{"id":10884192,"node_id":"MDEwOlJlcG9zaXRvcnkxMDg4NDE5Mg==","name":"copyit-app","full_name":"MMS-Projects/copyit-app","private":false,"owner":{"login":"MMS-Projects","id":16785204,"node_id":"MDEyOk9yZ2FuaXphdGlvbjE2Nzg1MjA0","gravatar_id":"","url":"https://api.github.com/users/MMS-Projects","type":"Organization","site_admin":false},"description":"This repository contains the desktop and Android app of CopyIt","fork":false,"url":"https://api.github.com/repos/MMS-Projects/copyit-app","created_at":"2013-06-23T12:40:04Z","updated_at":"2016-01-19T20:26:54Z","pushed_at":"2014-02-02T15:23:54Z","homepage":"http://copyit.dev.mms-projects.net/","size":17382,"stargazers_count":5,"watchers_count":5,"language":"Java","has_issues":true,"has_projects":true,"has_downloads":true,"has_wiki":true,"has_pages":false,"forks_count":2,"archived":false,"disabled":false,"open_issues_count":12,"forks":2,"open_issues":12,"watchers":5,"default_branch":"develop","permissions":{"admin":false,"push":false,"pull":true},"temp_clone_token":"","organization":{"login":"MMS-Projects","id":16785204,"node_id":"MDEyOk9yZ2FuaXphdGlvbjE2Nzg1MjA0","gravatar_id":"","url":"https://api.github.com/users/MMS-Projects","type":"Organization","site_admin":false},"network_count":2,"subscribers_count":5}