{"id":3460816,"node_id":"MDEwOlJlcG9zaXRvcnkzNDYwODE2","name":"metrics-graphite-pickle","full_name":"BrightcoveOS/metrics-graphite-pickle","private":false,"owner":{"login":"BrightcoveOS","id":442411,"node_id":"MDEyOk9yZ2FuaXphdGlvbjQ0MjQxMQ==","gravatar_id":"","url":"https://api.github.com/users/BrightcoveOS","type":"Organization","site_admin":false},"fork":false,"url":"https://api.github.com/repos/BrightcoveOS/metrics-graphite-pickle","created_at":"2012-02-16T15:03:43Z","updated_at":"2017-07-12T16:15:29Z","pushed_at":"2013-07-10T15:13:23Z","homepage":"","size":261,"stargazers_count":20,"watchers_count":20,"language":"Java","has_issues":true,"has_projects":true,"has_downloads":true,"has_wiki":true,"has_pages":false,"forks_count":6,"archived":false,"disabled":false,"open_issues_count":1,"license":{"key":"mit","name":"MIT License","spdx_id":"MIT","url":"https://api.github.com/licenses/mit","node_id":"MDc6TGljZW5zZTEz"},"forks":6,"open_issues":1,"watchers":20,"default_branch":"master","permissions":{"admin":false,"push":false,"pull":true},"temp_clone_token":"","organization":{"login":"BrightcoveOS","id":442411,"node_id":"MDEyOk9yZ2FuaXphdGlvbjQ0MjQxMQ==","gravatar_id":"","url":"https://api.github.com/users/BrightcoveOS","type":"Organization","site_admin":false},"network_count":6,"subscribers_count":9}