{"id":117416803,"node_id":"MDEwOlJlcG9zaXRvcnkxMTc0MTY4MDM=","name":"event-chains-extractor","full_name":"helloworld0909/event-chains-extractor","private":false,"owner":{"login":"helloworld0909","id":15411277,"node_id":"MDQ6VXNlcjE1NDExMjc3","gravatar_id":"","url":"https://api.github.com/users/helloworld0909","type":"User","site_admin":false},"description":"Implementation of event chains extraction algorithm using Dependency Parsing & Coreference Resolution of CoreNLP","fork":false,"url":"https://api.github.com/repos/helloworld0909/event-chains-extractor","created_at":"2018-01-14T09:13:44Z","updated_at":"2019-05-15T05:39:38Z","pushed_at":"2018-01-23T14:38:47Z","homepage":"","size":13,"stargazers_count":5,"watchers_count":5,"language":"Java","has_issues":true,"has_projects":true,"has_downloads":true,"has_wiki":true,"has_pages":false,"forks_count":0,"archived":false,"disabled":false,"open_issues_count":0,"license":{"key":"mit","name":"MIT License","spdx_id":"MIT","url":"https://api.github.com/licenses/mit","node_id":"MDc6TGljZW5zZTEz"},"forks":0,"open_issues":0,"watchers":5,"default_branch":"master","permissions":{"admin":false,"push":false,"pull":true},"temp_clone_token":"","network_count":0,"subscribers_count":1}