{"id":6541226,"node_id":"MDEwOlJlcG9zaXRvcnk2NTQxMjI2","name":"spring-ehcache-demo","full_name":"crashub/spring-ehcache-demo","private":false,"owner":{"login":"crashub","id":2612888,"node_id":"MDEyOk9yZ2FuaXphdGlvbjI2MTI4ODg=","gravatar_id":"","url":"https://api.github.com/users/crashub","type":"Organization","site_admin":false},"fork":false,"url":"https://api.github.com/repos/crashub/spring-ehcache-demo","created_at":"2012-11-05T08:25:44Z","updated_at":"2019-08-13T15:11:21Z","pushed_at":"2016-03-28T19:53:01Z","size":119,"stargazers_count":17,"watchers_count":17,"language":"Java","has_issues":true,"has_projects":true,"has_downloads":true,"has_wiki":true,"has_pages":false,"forks_count":12,"archived":false,"disabled":false,"open_issues_count":2,"forks":12,"open_issues":2,"watchers":17,"default_branch":"master","permissions":{"admin":false,"push":false,"pull":true},"temp_clone_token":"","organization":{"login":"crashub","id":2612888,"node_id":"MDEyOk9yZ2FuaXphdGlvbjI2MTI4ODg=","gravatar_id":"","url":"https://api.github.com/users/crashub","type":"Organization","site_admin":false},"network_count":12,"subscribers_count":6}