{"id":1270513,"node_id":"MDEwOlJlcG9zaXRvcnkxMjcwNTEz","name":"opencredo-couchdb","full_name":"opencredo/opencredo-couchdb","private":false,"owner":{"login":"opencredo","id":104106,"node_id":"MDEyOk9yZ2FuaXphdGlvbjEwNDEwNg==","gravatar_id":"","url":"https://api.github.com/users/opencredo","type":"Organization","site_admin":false},"description":"Opencredo Spring Integration Extensions for CouchDB","fork":false,"url":"https://api.github.com/repos/opencredo/opencredo-couchdb","created_at":"2011-01-19T10:48:28Z","updated_at":"2018-05-11T03:37:43Z","pushed_at":"2011-02-07T15:39:19Z","homepage":"http://www.opencredo.com","size":232,"stargazers_count":7,"watchers_count":7,"language":"Java","has_issues":true,"has_projects":true,"has_downloads":true,"has_wiki":true,"has_pages":false,"forks_count":1,"archived":false,"disabled":false,"open_issues_count":1,"license":{"key":"apache-2.0","name":"Apache License 2.0","spdx_id":"Apache-2.0","url":"https://api.github.com/licenses/apache-2.0","node_id":"MDc6TGljZW5zZTI="},"forks":1,"open_issues":1,"watchers":7,"default_branch":"master","permissions":{"admin":false,"push":false,"pull":true},"temp_clone_token":"","organization":{"login":"opencredo","id":104106,"node_id":"MDEyOk9yZ2FuaXphdGlvbjEwNDEwNg==","gravatar_id":"","url":"https://api.github.com/users/opencredo","type":"Organization","site_admin":false},"network_count":1,"subscribers_count":6}