{"id":12383298,"node_id":"MDEwOlJlcG9zaXRvcnkxMjM4MzI5OA==","name":"markdown-page-generator-plugin","full_name":"walokra/markdown-page-generator-plugin","private":false,"owner":{"login":"walokra","id":43757,"node_id":"MDQ6VXNlcjQzNzU3","gravatar_id":"","url":"https://api.github.com/users/walokra","type":"User","site_admin":false},"description":"Markdown to HTML Page Generator Maven Plugin","fork":false,"url":"https://api.github.com/repos/walokra/markdown-page-generator-plugin","created_at":"2013-08-26T15:57:02Z","updated_at":"2020-05-13T13:03:03Z","pushed_at":"2020-05-13T13:03:01Z","size":225,"stargazers_count":42,"watchers_count":42,"language":"Java","has_issues":true,"has_projects":true,"has_downloads":true,"has_wiki":true,"has_pages":false,"forks_count":39,"archived":false,"disabled":false,"open_issues_count":5,"license":{"key":"mit","name":"MIT License","spdx_id":"MIT","url":"https://api.github.com/licenses/mit","node_id":"MDc6TGljZW5zZTEz"},"forks":39,"open_issues":5,"watchers":42,"default_branch":"master","permissions":{"admin":false,"push":false,"pull":true},"temp_clone_token":"","network_count":39,"subscribers_count":6}