{"id":2656997,"node_id":"MDEwOlJlcG9zaXRvcnkyNjU2OTk3","name":"jtopia","full_name":"srijiths/jtopia","private":false,"owner":{"login":"srijiths","id":1046319,"node_id":"MDQ6VXNlcjEwNDYzMTk=","gravatar_id":"","url":"https://api.github.com/users/srijiths","type":"User","site_admin":false},"description":"Java clone for python term extractor topia.termextract","fork":false,"url":"https://api.github.com/repos/srijiths/jtopia","created_at":"2011-10-27T09:23:58Z","updated_at":"2020-03-23T05:44:29Z","pushed_at":"2014-08-22T07:26:14Z","homepage":"","size":11862,"stargazers_count":32,"watchers_count":32,"language":"Java","has_issues":true,"has_projects":true,"has_downloads":true,"has_wiki":true,"has_pages":false,"forks_count":18,"archived":false,"disabled":false,"open_issues_count":1,"forks":18,"open_issues":1,"watchers":32,"default_branch":"master","permissions":{"admin":false,"push":false,"pull":true},"temp_clone_token":"","network_count":18,"subscribers_count":8}