{"id":31772288,"node_id":"MDEwOlJlcG9zaXRvcnkzMTc3MjI4OA==","name":"WebSocketDemo","full_name":"yezilong9/WebSocketDemo","private":false,"owner":{"login":"yezilong9","id":6925885,"node_id":"MDQ6VXNlcjY5MjU4ODU=","gravatar_id":"","url":"https://api.github.com/users/yezilong9","type":"User","site_admin":false},"description":"使用netty构建的简单websocket，支持html5实时聊天","fork":false,"url":"https://api.github.com/repos/yezilong9/WebSocketDemo","created_at":"2015-03-06T14:15:49Z","updated_at":"2019-09-05T03:21:50Z","pushed_at":"2015-08-26T01:51:57Z","homepage":"","size":204,"stargazers_count":8,"watchers_count":8,"language":"Java","has_issues":true,"has_projects":true,"has_downloads":true,"has_wiki":true,"has_pages":false,"forks_count":10,"archived":false,"disabled":false,"open_issues_count":1,"forks":10,"open_issues":1,"watchers":8,"default_branch":"master","permissions":{"admin":false,"push":false,"pull":true},"temp_clone_token":"","network_count":10,"subscribers_count":1}