{"id":5793895,"node_id":"MDEwOlJlcG9zaXRvcnk1NzkzODk1","name":"ebean","full_name":"ebean-orm/ebean","private":false,"owner":{"login":"ebean-orm","id":3973790,"node_id":"MDEyOk9yZ2FuaXphdGlvbjM5NzM3OTA=","gravatar_id":"","url":"https://api.github.com/users/ebean-orm","type":"Organization","site_admin":false},"description":"Ebean ORM","fork":false,"url":"https://api.github.com/repos/ebean-orm/ebean","created_at":"2012-09-13T11:49:56Z","updated_at":"2020-06-23T10:03:37Z","pushed_at":"2020-06-23T10:03:34Z","homepage":"https://ebean.io","size":21345,"stargazers_count":1068,"watchers_count":1068,"language":"Java","has_issues":true,"has_projects":false,"has_downloads":true,"has_wiki":true,"has_pages":true,"forks_count":221,"archived":false,"disabled":false,"open_issues_count":17,"license":{"key":"other","name":"Other","spdx_id":"NOASSERTION","node_id":"MDc6TGljZW5zZTA="},"forks":221,"open_issues":17,"watchers":1068,"default_branch":"master","permissions":{"admin":false,"push":false,"pull":true},"temp_clone_token":"","organization":{"login":"ebean-orm","id":3973790,"node_id":"MDEyOk9yZ2FuaXphdGlvbjM5NzM3OTA=","gravatar_id":"","url":"https://api.github.com/users/ebean-orm","type":"Organization","site_admin":false},"network_count":221,"subscribers_count":78}