{"id":82419583,"node_id":"MDEwOlJlcG9zaXRvcnk4MjQxOTU4Mw==","name":"openhab-binding-zmote","full_name":"alexmaret/openhab-binding-zmote","private":false,"owner":{"login":"alexmaret","id":25718252,"node_id":"MDQ6VXNlcjI1NzE4MjUy","gravatar_id":"","url":"https://api.github.com/users/alexmaret","type":"User","site_admin":false},"description":"An OpenHAB2 binding for ZMote devices.","fork":false,"url":"https://api.github.com/repos/alexmaret/openhab-binding-zmote","created_at":"2017-02-18T22:17:22Z","updated_at":"2019-05-08T07:47:41Z","pushed_at":"2017-07-07T21:25:28Z","size":70,"stargazers_count":5,"watchers_count":5,"language":"Java","has_issues":true,"has_projects":true,"has_downloads":true,"has_wiki":true,"has_pages":false,"forks_count":0,"archived":false,"disabled":false,"open_issues_count":1,"license":{"key":"epl-1.0","name":"Eclipse Public License 1.0","spdx_id":"EPL-1.0","url":"https://api.github.com/licenses/epl-1.0","node_id":"MDc6TGljZW5zZTc="},"forks":0,"open_issues":1,"watchers":5,"default_branch":"master","permissions":{"admin":false,"push":false,"pull":true},"temp_clone_token":"","network_count":0,"subscribers_count":2}