{"id":15825329,"node_id":"MDEwOlJlcG9zaXRvcnkxNTgyNTMyOQ==","name":"SPIM_Registration","full_name":"fiji/SPIM_Registration","private":false,"owner":{"login":"fiji","id":458129,"node_id":"MDEyOk9yZ2FuaXphdGlvbjQ1ODEyOQ==","gravatar_id":"","url":"https://api.github.com/users/fiji","type":"Organization","site_admin":false},"description":"Deprecated, instead check out: https://github.com/preibischLab/multiview-reconstruction & https://github.com/PreibischLab/BigStitcher","fork":false,"url":"https://api.github.com/repos/fiji/SPIM_Registration","created_at":"2014-01-11T16:05:38Z","updated_at":"2020-05-20T16:31:11Z","pushed_at":"2020-05-20T16:31:08Z","homepage":"","size":5471,"stargazers_count":17,"watchers_count":17,"language":"Java","has_issues":true,"has_projects":true,"has_downloads":true,"has_wiki":true,"has_pages":false,"forks_count":20,"archived":false,"disabled":false,"open_issues_count":36,"license":{"key":"gpl-2.0","name":"GNU General Public License v2.0","spdx_id":"GPL-2.0","url":"https://api.github.com/licenses/gpl-2.0","node_id":"MDc6TGljZW5zZTg="},"forks":20,"open_issues":36,"watchers":17,"default_branch":"master","permissions":{"admin":false,"push":false,"pull":true},"temp_clone_token":"","organization":{"login":"fiji","id":458129,"node_id":"MDEyOk9yZ2FuaXphdGlvbjQ1ODEyOQ==","gravatar_id":"","url":"https://api.github.com/users/fiji","type":"Organization","site_admin":false},"network_count":20,"subscribers_count":22}