{"id":261659972,"node_id":"MDEwOlJlcG9zaXRvcnkyNjE2NTk5NzI=","name":"SimAnalyzer","full_name":"Col-E/SimAnalyzer","private":false,"owner":{"login":"Col-E","id":21371686,"node_id":"MDQ6VXNlcjIxMzcxNjg2","gravatar_id":"","url":"https://api.github.com/users/Col-E","type":"User","site_admin":false},"description":"An ASM analyzer implementation with minimal simulation to gather additional stackframe information.","fork":false,"url":"https://api.github.com/repos/Col-E/SimAnalyzer","created_at":"2020-05-06T05:24:49Z","updated_at":"2020-06-22T22:09:02Z","pushed_at":"2020-05-23T08:03:47Z","size":197,"stargazers_count":18,"watchers_count":18,"language":"Java","has_issues":true,"has_projects":true,"has_downloads":true,"has_wiki":true,"has_pages":false,"forks_count":1,"archived":false,"disabled":false,"open_issues_count":1,"license":{"key":"mit","name":"MIT License","spdx_id":"MIT","url":"https://api.github.com/licenses/mit","node_id":"MDc6TGljZW5zZTEz"},"forks":1,"open_issues":1,"watchers":18,"default_branch":"master","permissions":{"admin":false,"push":false,"pull":true},"temp_clone_token":"","network_count":1,"subscribers_count":3}